nexfil/__init__.py
nexfil/alt.py
nexfil/api.py
nexfil/cli.py
nexfil/headless.py
nexfil/metadata.json
nexfil/method.py
nexfil/printer.py
nexfil/redirect.py
nexfil/share.py
nexfil/string_case.py
nexfil/sub.py
nexfil/url.py
nexfil/url_store.json
nexfil/write_log.py
nexfil-1.0.6.dist-info/LICENSE
nexfil-1.0.6.dist-info/METADATA
nexfil-1.0.6.dist-info/WHEEL
nexfil-1.0.6.dist-info/entry_points.txt
nexfil-1.0.6.dist-info/top_level.txt
nexfil-1.0.6.dist-info/RECORD
