Metadata-Version: 2.1
Name: nexfil
Version: 1.0.6
Summary: OSINT tool for finding profiles by username
Author-email: thewhiteh4t <thewhiteh4t@protonmail.com>
License: MIT
Project-URL: Repository, https://github.com/thewhiteh4t/nexfil
Classifier: Operating System :: OS Independent
Classifier: License :: OSI Approved :: MIT License
Classifier: Programming Language :: Python :: 3
Classifier: Programming Language :: Python :: 3.10
Classifier: Programming Language :: Python :: 3.11
Requires-Python: >=3.10
License-File: LICENSE
Requires-Dist: aiohttp
Requires-Dist: tldextract
Requires-Dist: requests
Requires-Dist: packaging
Requires-Dist: undetected-chromedriver
